chumpy/__init__.py
chumpy/api_compatibility.py
chumpy/ch.py
chumpy/ch_ops.py
chumpy/ch_random.py
chumpy/extras.py
chumpy/linalg.py
chumpy/logic.py
chumpy/monitor.py
chumpy/np_tensordot.py
chumpy/optimization.py
chumpy/optimization_internal.py
chumpy/reordering.py
chumpy/test_ch.py
chumpy/test_inner_composition.py
chumpy/test_linalg.py
chumpy/test_optimization.py
chumpy/testing.py
chumpy/utils.py
chumpy/version.py
mocap_hands/__init__.py
mocap_hands/axengine_1754517934_1475099129.py
mocap_hands/dex_retargeting/CITATION.cff
mocap_hands/dex_retargeting/LICENSE
mocap_hands/dex_retargeting/assets/CITATION.cff
mocap_hands/dex_retargeting/assets/LICENSE
mocap_hands/dex_retargeting/assets/README.md
mocap_hands/dex_retargeting/assets/doc/gallery/ability-collision.png
mocap_hands/dex_retargeting/assets/doc/gallery/ability_rt.webp
mocap_hands/dex_retargeting/assets/doc/gallery/allegro-collision.png
mocap_hands/dex_retargeting/assets/doc/gallery/allegro_rt.webp
mocap_hands/dex_retargeting/assets/doc/gallery/barrett-collision.png
mocap_hands/dex_retargeting/assets/doc/gallery/bhand_rt.webp
mocap_hands/dex_retargeting/assets/doc/gallery/dclaw-collision.png
mocap_hands/dex_retargeting/assets/doc/gallery/dclaw_rt.webp
mocap_hands/dex_retargeting/assets/doc/gallery/inspire-collision.png
mocap_hands/dex_retargeting/assets/doc/gallery/inspire_rt.webp
mocap_hands/dex_retargeting/assets/doc/gallery/leap-collision.png
mocap_hands/dex_retargeting/assets/doc/gallery/leap_rt.webp
mocap_hands/dex_retargeting/assets/doc/gallery/panda-collision.png
mocap_hands/dex_retargeting/assets/doc/gallery/panda_rt.webp
mocap_hands/dex_retargeting/assets/doc/gallery/schunk-collision.png
mocap_hands/dex_retargeting/assets/doc/gallery/shadow-collision.png
mocap_hands/dex_retargeting/assets/doc/gallery/shadow_rt.webp
mocap_hands/dex_retargeting/assets/doc/gallery/svh_rt.webp
mocap_hands/dex_retargeting/assets/doc/improved_collision/new_collision.png
mocap_hands-3.2.13.dist-info/METADATA
mocap_hands-3.2.13.dist-info/WHEEL
mocap_hands-3.2.13.dist-info/RECORD
