Metadata-Version: 2.1
Name: mocap-hands
Version: 3.2.13
Summary: Motion capture operation for hands for moveai's engine.
Keywords: MotionOps,Moveai
Author: move.ai
Author-email: info@move.ai
Requires-Python: >=3.10,<4.0
Classifier: Programming Language :: Python :: 3
Classifier: Programming Language :: Python :: 3.10
Classifier: Programming Language :: Python :: 3.11
Classifier: Programming Language :: Python :: 3.12
Requires-Dist: anytree (>=2.13.0,<3.0.0)
Requires-Dist: einops (>=0.6.1,<0.7.0)
Requires-Dist: gradio (>=5.28.0,<6.0.0)
Requires-Dist: hydra-colorlog (>=1.2.0,<2.0.0)
Requires-Dist: hydra-core (>=1.3.2,<2.0.0)
Requires-Dist: hydra-submitit-launcher (>=1.2.0,<2.0.0)
Requires-Dist: lxml (>=5.4.0,<6.0.0)
Requires-Dist: mocap-base (>=2.5.1,<3.0.0)
Requires-Dist: mocap_settings (>=1.15.1,<2.0.0)
Requires-Dist: nlopt (>=2.7.1,<3.0.0)
Requires-Dist: numpy (>=1.24.3,<2.0.0)
Requires-Dist: pandas (>=2.2.3,<3.0.0)
Requires-Dist: pin (>=2.6.20,<3.0.0)
Requires-Dist: pyrender (>=0.1.45,<0.2.0)
Requires-Dist: pyrootutils (>=1.0.4,<2.0.0)
Requires-Dist: pytorch-lightning (>=1.9.5,<2.0.0)
Requires-Dist: pytransform3d (>=3.14.0,<4.0.0)
Requires-Dist: rich (>=13.9.4,<14.0.0)
Requires-Dist: scikit-image (>=0.25.2,<0.26.0)
Requires-Dist: smplx (>=0.1.28,<0.2.0)
Requires-Dist: timm (>=0.9.16,<0.10.0)
Requires-Dist: torch (==1.13.0)
Requires-Dist: torchvision (==0.14.0)
Requires-Dist: ultralytics (>=8.3.163,<9.0.0)
Requires-Dist: update (>=0.0.1,<0.0.2)
Requires-Dist: webdataset (>=0.2.111,<0.3.0)
Requires-Dist: xtcocotools (==1.13)
Requires-Dist: yacs (>=0.1.8,<0.2.0)
